[
	{
		"inputs": [
			{
				"internalType": "address",
				"name": "owner",
				"type": "address"
			}
		],
		"stateMutability": "nonpayable",
		"type": "constructor"
	},
	{
		"inputs": [
			{
				"internalType": "address",
				"name": "owner",
				"type": "address"
			}
		],
		"name": "OwnableInvalidOwner",
		"type": "error"
	},
	{
		"inputs": [
			{
				"internalType": "address",
				"name": "account",
				"type": "address"
			}
		],
		"name": "OwnableUnauthorizedAccount",
		"type": "error"
	},
	{
		"anonymous": false,
		"inputs": [
			{
				"indexed": true,
				"internalType": "address",
				"name": "previousOwner",
				"type": "address"
			},
			{
				"indexed": true,
				"internalType": "address",
				"name": "newOwner",
				"type": "address"
			}
		],
		"name": "OwnershipTransferred",
		"type": "event"
	},
	{
		"anonymous": false,
		"inputs": [
			{
				"indexed": false,
				"internalType": "address",
				"name": "user",
				"type": "address"
			},
			{
				"indexed": false,
				"internalType": "uint256",
				"name": "amount",
				"type": "uint256"
			}
		],
		"name": "PointsClaimed",
		"type": "event"
	},
	{
		"anonymous": false,
		"inputs": [
			{
				"indexed": false,
				"internalType": "address",
				"name": "user",
				"type": "address"
			},
			{
				"indexed": false,
				"internalType": "uint256",
				"name": "pointToSwap",
				"type": "uint256"
			},
			{
				"indexed": false,
				"internalType": "uint256",
				"name": "paymentTokenRecieved",
				"type": "uint256"
			},
			{
				"indexed": false,
				"internalType": "uint256",
				"name": "_fees",
				"type": "uint256"
			}
		],
		"name": "swap",
		"type": "event"
	},
	{
		"inputs": [
			{
				"internalType": "uint256",
				"name": "pointToSwap",
				"type": "uint256"
			}
		],
		"name": "checkAmountToRecive",
		"outputs": [
			{
				"internalType": "uint256",
				"name": "",
				"type": "uint256"
			}
		],
		"stateMutability": "view",
		"type": "function"
	},
	{
		"inputs": [
			{
				"internalType": "address",
				"name": "user",
				"type": "address"
			},
			{
				"internalType": "uint256",
				"name": "amount",
				"type": "uint256"
			}
		],
		"name": "claimPoints",
		"outputs": [],
		"stateMutability": "nonpayable",
		"type": "function"
	},
	{
		"inputs": [],
		"name": "init",
		"outputs": [],
		"stateMutability": "nonpayable",
		"type": "function"
	},
	{
		"inputs": [],
		"name": "owner",
		"outputs": [
			{
				"internalType": "address",
				"name": "",
				"type": "address"
			}
		],
		"stateMutability": "view",
		"type": "function"
	},
	{
		"inputs": [],
		"name": "renounceOwnership",
		"outputs": [],
		"stateMutability": "nonpayable",
		"type": "function"
	},
	{
		"inputs": [
			{
				"internalType": "uint256",
				"name": "_pointsMin",
				"type": "uint256"
			}
		],
		"name": "setMinPointsToSWap",
		"outputs": [],
		"stateMutability": "nonpayable",
		"type": "function"
	},
	{
		"inputs": [
			{
				"internalType": "uint256",
				"name": "_fee",
				"type": "uint256"
			}
		],
		"name": "setPaymentDepositfees",
		"outputs": [],
		"stateMutability": "nonpayable",
		"type": "function"
	},
	{
		"inputs": [
			{
				"internalType": "uint256",
				"name": "_rate",
				"type": "uint256"
			}
		],
		"name": "setRate",
		"outputs": [],
		"stateMutability": "nonpayable",
		"type": "function"
	},
	{
		"inputs": [
			{
				"internalType": "uint256",
				"name": "_fee",
				"type": "uint256"
			}
		],
		"name": "setWithdrawalFee",
		"outputs": [],
		"stateMutability": "nonpayable",
		"type": "function"
	},
	{
		"inputs": [
			{
				"internalType": "address",
				"name": "paymentAddress",
				"type": "address"
			},
			{
				"internalType": "address",
				"name": "pointsaddress",
				"type": "address"
			}
		],
		"name": "setpaymentTokenAndpoints",
		"outputs": [],
		"stateMutability": "nonpayable",
		"type": "function"
	},
	{
		"inputs": [
			{
				"internalType": "address",
				"name": "user",
				"type": "address"
			},
			{
				"internalType": "uint256",
				"name": "pointToSwap",
				"type": "uint256"
			}
		],
		"name": "swapToPaymentCoin",
		"outputs": [],
		"stateMutability": "nonpayable",
		"type": "function"
	},
	{
		"inputs": [
			{
				"internalType": "address",
				"name": "newOwner",
				"type": "address"
			}
		],
		"name": "transferOwnership",
		"outputs": [],
		"stateMutability": "nonpayable",
		"type": "function"
	},
	{
		"inputs": [
			{
				"internalType": "address",
				"name": "feeTakerAddress",
				"type": "address"
			}
		],
		"name": "withdrawfees",
		"outputs": [],
		"stateMutability": "nonpayable",
		"type": "function"
	}
]